AUTHORS
INSTALL
LICENSE
MANIFEST.in
NOTICE
README
requirements.txt
setup.cfg
setup.py
docs/Makefile
docs/conf.py
docs/configuration.rst
docs/faq.rst
docs/index.rst
docs/installation.rst
docs/introduction.rst
docs/make.bat
docs/usage.rst
src/django_oembed_works.egg-info/PKG-INFO
src/django_oembed_works.egg-info/SOURCES.txt
src/django_oembed_works.egg-info/dependency_links.txt
src/django_oembed_works.egg-info/top_level.txt
src/oembed_works/__init__.py
src/oembed_works/admin.py
src/oembed_works/exceptions.py
src/oembed_works/models.py
src/oembed_works/oembed.py
src/oembed_works/settings.py
src/oembed_works/tests.py
src/oembed_works/utils.py
src/oembed_works/management/__init__.py
src/oembed_works/management/commands/__init__.py
src/oembed_works/management/commands/clear_oembed_cache.py
src/oembed_works/templates/oembed_works/link.html
src/oembed_works/templates/oembed_works/photo.html
src/oembed_works/templates/oembed_works/rich.html
src/oembed_works/templates/oembed_works/video.html
src/oembed_works/templatetags/__init__.py
src/oembed_works/templatetags/oembed_works_tags.py