Metadata-Version: 1.0
Name: django-oembed-works
Version: 0.2.1
Summary: django-oembed-works is a Django app that provides support for the oEmbed format.
Home-page: http://www.codetrax.org/projects/django-oembed-works
Author: George Notaras
Author-email: gnot [at] g-loaded.eu
License: Apache License version 2
Download-URL: https://source.codetrax.org/hgroot/django-oembed-works
Platform: any
Classifier: Development Status :: 4 - Beta
Classifier: Environment :: Web Environment
Classifier: Framework :: Django
Classifier: Intended Audience :: Developers
Classifier: License :: OSI Approved :: Apache Software License
Classifier: Natural Language :: English
Classifier: Operating System :: OS Independent
Classifier: Programming Language :: Python
Classifier: Topic :: Internet :: WWW/HTTP :: Dynamic Content
Classifier: Topic :: Software Development :: Libraries :: Application Frameworks
Classifier: Topic :: Software Development :: Libraries :: Python Modules
